django_twc_toolbox/__init__.py
django_twc_toolbox/_typing.py
django_twc_toolbox/admin.py
django_twc_toolbox/apps.py
django_twc_toolbox/conf.py
django_twc_toolbox/fields.py
django_twc_toolbox/middleware.py
django_twc_toolbox/models.py
django_twc_toolbox/numbers.py
django_twc_toolbox/paginator.py
django_twc_toolbox/py.typed
django_twc_toolbox/sentry.py
django_twc_toolbox/urls.py
django_twc_toolbox/views.py
django_twc_toolbox/crud/__init__.py
django_twc_toolbox/crud/views.py
django_twc_toolbox/crud/templates/neapolitan/object_confirm_delete.html
django_twc_toolbox/crud/templates/neapolitan/object_detail.html
django_twc_toolbox/crud/templates/neapolitan/object_form.html
django_twc_toolbox/crud/templates/neapolitan/object_list.html
django_twc_toolbox/crud/templates/neapolitan/partial/detail.html
django_twc_toolbox/crud/templates/neapolitan/partial/list.html
django_twc_toolbox/crud/templatetags/__init__.py
django_twc_toolbox/crud/templatetags/neapolitan.py
django_twc_toolbox/management/__init__.py
django_twc_toolbox/management/commands/__init__.py
django_twc_toolbox/management/commands/copy_template.py
django_twc_toolbox/management/commands/createsuperuser.py
django_twc_toolbox/management/commands/list_templates.py
django_twc_toolbox/templatetags/__init__.py
django_twc_toolbox/templatetags/django_twc_toolbox.py
django_twc_toolbox-0.18.0.dist-info/METADATA
django_twc_toolbox-0.18.0.dist-info/WHEEL
django_twc_toolbox-0.18.0.dist-info/licenses/AUTHORS.md
django_twc_toolbox-0.18.0.dist-info/licenses/LICENSE
django_twc_toolbox-0.18.0.dist-info/RECORD
