Metadata-Version: 2.4
Name: django-twc-toolbox
Version: 0.18.0
Summary: Various tools for Django projects at The Westervelt Company.
Project-URL: Documentation, https://django-twc-toolbox.westervelt.dev/
Project-URL: Issues, https://github.com/westerveltco/django-twc-toolbox/issues
Project-URL: Source, https://github.com/westerveltco/django-twc-toolbox
Author-email: Josh Thomas <josh@joshthomas.dev>
License: MIT License
License-File: AUTHORS.md
License-File: LICENSE
Classifier: Development Status :: 3 - Alpha
Classifier: Framework :: Django
Classifier: Framework :: Django :: 4.2
Classifier: Framework :: Django :: 5.0
Classifier: Framework :: Django :: 5.1
Classifier: License :: OSI Approved :: MIT License
Classifier: Operating System :: OS Independent
Classifier: Programming Language :: Python
Classifier: Programming Language :: Python :: 3
Classifier: Programming Language :: Python :: 3 :: Only
Classifier: Programming Language :: Python :: 3.10
Classifier: Programming Language :: Python :: 3.11
Classifier: Programming Language :: Python :: 3.12
Classifier: Programming Language :: Python :: 3.13
Classifier: Programming Language :: Python :: Implementation :: CPython
Requires-Python: >=3.10
Requires-Dist: django>=4.2
Provides-Extra: crud
Requires-Dist: django-htmx; extra == 'crud'
Requires-Dist: django-tables2; extra == 'crud'
Requires-Dist: django-template-partials; extra == 'crud'
Requires-Dist: neapolitan; extra == 'crud'
Provides-Extra: cuid
Requires-Dist: cuid; extra == 'cuid'
Requires-Dist: django-charid-field; extra == 'cuid'
Provides-Extra: dev
Requires-Dist: bumpver; extra == 'dev'
Requires-Dist: copier; extra == 'dev'
Requires-Dist: copier-templates-extensions; extra == 'dev'
Requires-Dist: coverage[toml]; extra == 'dev'
Requires-Dist: cuid; extra == 'dev'
Requires-Dist: django-charid-field; extra == 'dev'
Requires-Dist: django-htmx; extra == 'dev'
Requires-Dist: django-simple-history; extra == 'dev'
Requires-Dist: django-stubs; extra == 'dev'
Requires-Dist: django-stubs-ext; extra == 'dev'
Requires-Dist: django-tables2; extra == 'dev'
Requires-Dist: django-template-partials; extra == 'dev'
Requires-Dist: faker; extra == 'dev'
Requires-Dist: hatch; extra == 'dev'
Requires-Dist: model-bakery; extra == 'dev'
Requires-Dist: mypy; extra == 'dev'
Requires-Dist: neapolitan; extra == 'dev'
Requires-Dist: nox[uv]; extra == 'dev'
Requires-Dist: pytest; extra == 'dev'
Requires-Dist: pytest-cov; extra == 'dev'
Requires-Dist: pytest-django; extra == 'dev'
Requires-Dist: pytest-randomly; extra == 'dev'
Requires-Dist: pytest-reverse; extra == 'dev'
Requires-Dist: pytest-xdist; extra == 'dev'
Requires-Dist: ruff; extra == 'dev'
Requires-Dist: sentry-sdk[django]; extra == 'dev'
Provides-Extra: docs
Requires-Dist: cogapp; extra == 'docs'
Requires-Dist: furo; extra == 'docs'
Requires-Dist: myst-parser; extra == 'docs'
Requires-Dist: sphinx; extra == 'docs'
Requires-Dist: sphinx-autobuild; extra == 'docs'
Requires-Dist: sphinx-autodoc2; extra == 'docs'
Requires-Dist: sphinx-copybutton; extra == 'docs'
Requires-Dist: sphinx-inline-tabs; extra == 'docs'
Provides-Extra: history
Requires-Dist: django-simple-history; extra == 'history'
Provides-Extra: lint
Requires-Dist: pre-commit; extra == 'lint'
Provides-Extra: sentry
Requires-Dist: sentry-sdk[django]; extra == 'sentry'
